pyramid_flamegraph/__init__.py
pyramid_flamegraph/flamegraph.pl
pyramid_flamegraph/flamegraphwrap.py
pyramid_flamegraph-0.1.1.dist-info/METADATA
pyramid_flamegraph-0.1.1.dist-info/RECORD
pyramid_flamegraph-0.1.1.dist-info/WHEEL
pyramid_flamegraph-0.1.1.dist-info/top_level.txt
