Metadata-Version: 2.1
Name: pyramid-flamegraph
Version: 0.1.1
Summary: Pyramid tween to generate a flamegraph log for every request
Home-page: https://gitlab.com/hhatto/pyramid_flamegraph
Author: Hideo Hattori
Author-email: hhatto.jp@gmail.com
License: MIT
Keywords: pyramid,flamegraph,profile
Platform: UNKNOWN
Classifier: License :: OSI Approved :: MIT License
Classifier: Programming Language :: Python :: 3
Classifier: Programming Language :: Python :: 3.6
Classifier: Programming Language :: Python :: 3.7
